{
  "summaries": [
    {
      "seed": "251052-0",
      "winner": "red",
      "ticks": 550,
      "redAlive": 2,
      "blueAlive": 0,
      "redEnergy": 126,
      "blueEnergy": 0
    },
    {
      "seed": "251052-8",
      "winner": "blue",
      "ticks": 370,
      "redAlive": 0,
      "blueAlive": 4,
      "redEnergy": 0,
      "blueEnergy": 117
    },
    {
      "seed": "251052-16",
      "winner": "blue",
      "ticks": 757,
      "redAlive": 0,
      "blueAlive": 3,
      "redEnergy": 0,
      "blueEnergy": 136
    },
    {
      "seed": "251052-24",
      "winner": "blue",
      "ticks": 478,
      "redAlive": 0,
      "blueAlive": 4,
      "redEnergy": 0,
      "blueEnergy": 195
    },
    {
      "seed": "251052-1",
      "winner": "red",
      "ticks": 550,
      "redAlive": 2,
      "blueAlive": 0,
      "redEnergy": 126,
      "blueEnergy": 0
    },
    {
      "seed": "251052-9",
      "winner": "blue",
      "ticks": 370,
      "redAlive": 0,
      "blueAlive": 4,
      "redEnergy": 0,
      "blueEnergy": 117
    },
    {
      "seed": "251052-17",
      "winner": "blue",
      "ticks": 757,
      "redAlive": 0,
      "blueAlive": 3,
      "redEnergy": 0,
      "blueEnergy": 136
    },
    {
      "seed": "251052-2",
      "winner": "red",
      "ticks": 550,
      "redAlive": 2,
      "blueAlive": 0,
      "redEnergy": 126,
      "blueEnergy": 0
    },
    {
      "seed": "251052-10",
      "winner": "blue",
      "ticks": 370,
      "redAlive": 0,
      "blueAlive": 4,
      "redEnergy": 0,
      "blueEnergy": 117
    },
    {
      "seed": "251052-18",
      "winner": "blue",
      "ticks": 757,
      "redAlive": 0,
      "blueAlive": 3,
      "redEnergy": 0,
      "blueEnergy": 136
    },
    {
      "seed": "251052-3",
      "winner": "red",
      "ticks": 550,
      "redAlive": 2,
      "blueAlive": 0,
      "redEnergy": 126,
      "blueEnergy": 0
    },
    {
      "seed": "251052-11",
      "winner": "blue",
      "ticks": 370,
      "redAlive": 0,
      "blueAlive": 4,
      "redEnergy": 0,
      "blueEnergy": 117
    },
    {
      "seed": "251052-19",
      "winner": "blue",
      "ticks": 757,
      "redAlive": 0,
      "blueAlive": 3,
      "redEnergy": 0,
      "blueEnergy": 136
    },
    {
      "seed": "251052-4",
      "winner": "red",
      "ticks": 550,
      "redAlive": 2,
      "blueAlive": 0,
      "redEnergy": 126,
      "blueEnergy": 0
    },
    {
      "seed": "251052-12",
      "winner": "blue",
      "ticks": 370,
      "redAlive": 0,
      "blueAlive": 4,
      "redEnergy": 0,
      "blueEnergy": 117
    },
    {
      "seed": "251052-20",
      "winner": "blue",
      "ticks": 757,
      "redAlive": 0,
      "blueAlive": 3,
      "redEnergy": 0,
      "blueEnergy": 136
    },
    {
      "seed": "251052-5",
      "winner": "red",
      "ticks": 550,
      "redAlive": 2,
      "blueAlive": 0,
      "redEnergy": 126,
      "blueEnergy": 0
    },
    {
      "seed": "251052-13",
      "winner": "blue",
      "ticks": 370,
      "redAlive": 0,
      "blueAlive": 4,
      "redEnergy": 0,
      "blueEnergy": 117
    },
    {
      "seed": "251052-21",
      "winner": "blue",
      "ticks": 757,
      "redAlive": 0,
      "blueAlive": 3,
      "redEnergy": 0,
      "blueEnergy": 136
    },
    {
      "seed": "251052-6",
      "winner": "red",
      "ticks": 550,
      "redAlive": 2,
      "blueAlive": 0,
      "redEnergy": 126,
      "blueEnergy": 0
    },
    {
      "seed": "251052-14",
      "winner": "blue",
      "ticks": 370,
      "redAlive": 0,
      "blueAlive": 4,
      "redEnergy": 0,
      "blueEnergy": 117
    },
    {
      "seed": "251052-22",
      "winner": "blue",
      "ticks": 757,
      "redAlive": 0,
      "blueAlive": 3,
      "redEnergy": 0,
      "blueEnergy": 136
    },
    {
      "seed": "251052-7",
      "winner": "red",
      "ticks": 550,
      "redAlive": 2,
      "blueAlive": 0,
      "redEnergy": 126,
      "blueEnergy": 0
    },
    {
      "seed": "251052-15",
      "winner": "blue",
      "ticks": 370,
      "redAlive": 0,
      "blueAlive": 4,
      "redEnergy": 0,
      "blueEnergy": 117
    },
    {
      "seed": "251052-23",
      "winner": "blue",
      "ticks": 757,
      "redAlive": 0,
      "blueAlive": 3,
      "redEnergy": 0,
      "blueEnergy": 136
    }
  ],
  "aggregate": {
    "matches": 25,
    "redWins": 8,
    "blueWins": 17,
    "draws": 0,
    "avgTicks": 555.76,
    "avgRedAlive": 0.64,
    "avgBlueAlive": 2.4,
    "avgRedEnergy": 40.32,
    "avgBlueEnergy": 88.76,
    "baseSeed": "251052",
    "concurrency": 8
  }
}