{
  "summaries": [
    {
      "seed": "251052-0",
      "winner": "blue",
      "ticks": 1051,
      "redAlive": 0,
      "blueAlive": 1,
      "redEnergy": 0,
      "blueEnergy": 9
    },
    {
      "seed": "251052-8",
      "winner": "blue",
      "ticks": 466,
      "redAlive": 0,
      "blueAlive": 4,
      "redEnergy": 0,
      "blueEnergy": 192
    },
    {
      "seed": "251052-16",
      "winner": "red",
      "ticks": 536,
      "redAlive": 3,
      "blueAlive": 0,
      "redEnergy": 104,
      "blueEnergy": 0
    },
    {
      "seed": "251052-24",
      "winner": "blue",
      "ticks": 513,
      "redAlive": 0,
      "blueAlive": 3,
      "redEnergy": 0,
      "blueEnergy": 261
    },
    {
      "seed": "251052-1",
      "winner": "blue",
      "ticks": 1051,
      "redAlive": 0,
      "blueAlive": 1,
      "redEnergy": 0,
      "blueEnergy": 9
    },
    {
      "seed": "251052-9",
      "winner": "blue",
      "ticks": 466,
      "redAlive": 0,
      "blueAlive": 4,
      "redEnergy": 0,
      "blueEnergy": 192
    },
    {
      "seed": "251052-17",
      "winner": "red",
      "ticks": 536,
      "redAlive": 3,
      "blueAlive": 0,
      "redEnergy": 104,
      "blueEnergy": 0
    },
    {
      "seed": "251052-2",
      "winner": "blue",
      "ticks": 1051,
      "redAlive": 0,
      "blueAlive": 1,
      "redEnergy": 0,
      "blueEnergy": 9
    },
    {
      "seed": "251052-10",
      "winner": "blue",
      "ticks": 466,
      "redAlive": 0,
      "blueAlive": 4,
      "redEnergy": 0,
      "blueEnergy": 192
    },
    {
      "seed": "251052-18",
      "winner": "red",
      "ticks": 536,
      "redAlive": 3,
      "blueAlive": 0,
      "redEnergy": 104,
      "blueEnergy": 0
    },
    {
      "seed": "251052-3",
      "winner": "blue",
      "ticks": 1051,
      "redAlive": 0,
      "blueAlive": 1,
      "redEnergy": 0,
      "blueEnergy": 9
    },
    {
      "seed": "251052-11",
      "winner": "blue",
      "ticks": 466,
      "redAlive": 0,
      "blueAlive": 4,
      "redEnergy": 0,
      "blueEnergy": 192
    },
    {
      "seed": "251052-19",
      "winner": "red",
      "ticks": 536,
      "redAlive": 3,
      "blueAlive": 0,
      "redEnergy": 104,
      "blueEnergy": 0
    },
    {
      "seed": "251052-4",
      "winner": "blue",
      "ticks": 1051,
      "redAlive": 0,
      "blueAlive": 1,
      "redEnergy": 0,
      "blueEnergy": 9
    },
    {
      "seed": "251052-12",
      "winner": "blue",
      "ticks": 466,
      "redAlive": 0,
      "blueAlive": 4,
      "redEnergy": 0,
      "blueEnergy": 192
    },
    {
      "seed": "251052-20",
      "winner": "red",
      "ticks": 536,
      "redAlive": 3,
      "blueAlive": 0,
      "redEnergy": 104,
      "blueEnergy": 0
    },
    {
      "seed": "251052-5",
      "winner": "blue",
      "ticks": 1051,
      "redAlive": 0,
      "blueAlive": 1,
      "redEnergy": 0,
      "blueEnergy": 9
    },
    {
      "seed": "251052-13",
      "winner": "blue",
      "ticks": 466,
      "redAlive": 0,
      "blueAlive": 4,
      "redEnergy": 0,
      "blueEnergy": 192
    },
    {
      "seed": "251052-21",
      "winner": "red",
      "ticks": 536,
      "redAlive": 3,
      "blueAlive": 0,
      "redEnergy": 104,
      "blueEnergy": 0
    },
    {
      "seed": "251052-6",
      "winner": "blue",
      "ticks": 1051,
      "redAlive": 0,
      "blueAlive": 1,
      "redEnergy": 0,
      "blueEnergy": 9
    },
    {
      "seed": "251052-14",
      "winner": "blue",
      "ticks": 466,
      "redAlive": 0,
      "blueAlive": 4,
      "redEnergy": 0,
      "blueEnergy": 192
    },
    {
      "seed": "251052-22",
      "winner": "red",
      "ticks": 536,
      "redAlive": 3,
      "blueAlive": 0,
      "redEnergy": 104,
      "blueEnergy": 0
    },
    {
      "seed": "251052-7",
      "winner": "blue",
      "ticks": 1051,
      "redAlive": 0,
      "blueAlive": 1,
      "redEnergy": 0,
      "blueEnergy": 9
    },
    {
      "seed": "251052-15",
      "winner": "blue",
      "ticks": 466,
      "redAlive": 0,
      "blueAlive": 4,
      "redEnergy": 0,
      "blueEnergy": 192
    },
    {
      "seed": "251052-23",
      "winner": "red",
      "ticks": 536,
      "redAlive": 3,
      "blueAlive": 0,
      "redEnergy": 104,
      "blueEnergy": 0
    }
  ],
  "aggregate": {
    "matches": 25,
    "redWins": 8,
    "blueWins": 17,
    "draws": 0,
    "avgTicks": 677.48,
    "avgRedAlive": 0.96,
    "avgBlueAlive": 1.72,
    "avgRedEnergy": 33.28,
    "avgBlueEnergy": 74.76,
    "baseSeed": "251052",
    "concurrency": 8
  }
}